check_build/__init__.py
check_build/__main__.py
check_build/defs.py
check_build/parse.py
check_build/process.py
check_build/util.py
check_build-0.1.1.dist-info/METADATA
check_build-0.1.1.dist-info/WHEEL
check_build-0.1.1.dist-info/entry_points.txt
check_build-0.1.1.dist-info/RECORD
