Metadata-Version: 2.4
Name: check-build
Version: 0.1.1
Summary: Check whether some example programs can be compiled and built
Project-URL: Homepage, https://gitlab.com/ppentchev/check-build
Project-URL: Changes, https://gitlab.com/ppentchev/check-build/-/blob/main/CHANGELOG.md
Project-URL: Issue Tracker, https://gitlab.com/ppentchev/check-build/-/issues
Project-URL: Source Code, https://gitlab.com/ppentchev/check-build
Author-email: Peter Pentchev <roam@ringlet.net>
Classifier: Development Status :: 4 - Beta
Classifier: Environment :: Console
Classifier: Intended Audience :: Developers
Classifier: License :: DFSG approved
Classifier: License :: Freely Distributable
Classifier: License :: OSI Approved
Classifier: License :: OSI Approved :: BSD License
Classifier: Operating System :: POSIX
Classifier: Operating System :: Unix
Classifier: Programming Language :: Python
Classifier: Programming Language :: Python :: 3
Classifier: Programming Language :: Python :: 3 :: Only
Classifier: Programming Language :: Python :: 3.11
Classifier: Programming Language :: Python :: 3.12
Classifier: Programming Language :: Python :: 3.13
Classifier: Programming Language :: Python :: 3.14
Classifier: Programming Language :: Python :: Implementation :: CPython
Classifier: Topic :: Software Development
Classifier: Topic :: Software Development :: Testing
Classifier: Topic :: Utilities
Classifier: Typing :: Typed
Requires-Python: >=3.11
Requires-Dist: click<9,>=8.1
Requires-Dist: media-type-version<0.3,>=0.2
Requires-Dist: typedload<3,>=2.22
